string_algorithms/utils.py
string_algorithms/suffix_array.py
string_algorithms/rmq.py
string_algorithms/node_mixins.py
string_algorithms/kmp.py
string_algorithms/naive_find.py
string_algorithms/tree.py
string_algorithms/__init__.py
string_algorithms/lca.py
string_algorithms/trie.py
string_algorithms/aho_corrasick.py
string_algorithms/exact_string_matching.py
string_algorithms-0.5.0.dist-info/METADATA
string_algorithms-0.5.0.dist-info/metadata.json
string_algorithms-0.5.0.dist-info/DESCRIPTION.rst
string_algorithms-0.5.0.dist-info/WHEEL
string_algorithms-0.5.0.dist-info/top_level.txt
string_algorithms-0.5.0.dist-info/zip-safe
string_algorithms-0.5.0.dist-info/RECORD
