Metadata-Version: 2.0
Name: string-algorithms
Version: 0.5.0
Summary: Collection of various string algorithms, including KMP, Aho-Corasick, Trie, SuffixArrays
Home-page: https://github.com/mhozza/string_algorithms
Author: Michal Hozza
Author-email: mhozza@gmail.com
License: MIT
Keywords: string_algorithms
Platform: UNKNOWN
Classifier: Development Status :: 2 - Pre-Alpha
Classifier: Intended Audience :: Developers
Classifier: License :: OSI Approved :: MIT License
Classifier: Natural Language :: English
Classifier: Programming Language :: Python :: 2
Classifier: Programming Language :: Python :: 2.6
Classifier: Programming Language :: Python :: 2.7
Classifier: Programming Language :: Python :: 3
Classifier: Programming Language :: Python :: 3.3
Classifier: Programming Language :: Python :: 3.4
Classifier: Programming Language :: Python :: 3.5
